debuntu_tools/__init__.py
debuntu_tools/kernel_manager.py
debuntu_tools/nodejs_installer.py
debuntu_tools/remote_reboot.py
debuntu_tools/remote_unlock.py
debuntu_tools/upgrade_system.py
debuntu_tools-0.9.1.dist-info/LICENSE.txt
debuntu_tools-0.9.1.dist-info/METADATA
debuntu_tools-0.9.1.dist-info/WHEEL
debuntu_tools-0.9.1.dist-info/entry_points.txt
debuntu_tools-0.9.1.dist-info/top_level.txt
debuntu_tools-0.9.1.dist-info/RECORD
