Metadata-Version: 2.1
Name: debuntu-tools
Version: 0.9.1
Summary: Debian and Ubuntu system administration tools
Home-page: https://debuntu-tools.readthedocs.io/
Author: Peter Odding
Author-email: peter@peterodding.com
License: MIT
Platform: UNKNOWN
Classifier: Development Status :: 3 - Alpha
Classifier: Environment :: Console
Classifier: Intended Audience :: Developers
Classifier: Intended Audience :: Information Technology
Classifier: Intended Audience :: System Administrators
Classifier: License :: OSI Approved :: MIT License
Classifier: Natural Language :: English
Classifier: Operating System :: POSIX
Classifier: Operating System :: POSIX :: Linux
Classifier: Operating System :: Unix
Classifier: Programming Language :: Python
Classifier: Programming Language :: Python :: 2
Classifier: Programming Language :: Python :: 2.7
Classifier: Programming Language :: Python :: Implementation :: CPython
Classifier: Topic :: Software Development
Classifier: Topic :: Software Development :: Libraries
Classifier: Topic :: Software Development :: Libraries :: Python Modules
Classifier: Topic :: System :: Systems Administration
Classifier: Topic :: Utilities
Requires-Python: >=2.7, !=3.0.*, !=3.1.*, !=3.2.*, !=3.3.*, !=3.4.*
Requires-Dist: apt-mirror-updater (>=7.2)
Requires-Dist: coloredlogs (>=14.0)
Requires-Dist: deb-pkg-tools (>=8.3)
Requires-Dist: executor (>=23.1)
Requires-Dist: humanfriendly (>=8.2)
Requires-Dist: linux-utils (>=0.7)
Requires-Dist: property-manager (>=3.0)
Requires-Dist: six (>=1.14.0)
Requires-Dist: update-dotdee (>=6.0)
Requires-Dist: verboselogs (>=1.7)
